odoo/addons/foodcoopbcn/__init__.py
odoo/addons/foodcoopbcn/__manifest__.py
odoo/addons/foodcoopbcn/controllers/__init__.py
odoo/addons/foodcoopbcn/controllers/website_subscription.py
odoo/addons/foodcoopbcn/data/ir_default.xml
odoo/addons/foodcoopbcn/data/report_paperformat.xml
odoo/addons/foodcoopbcn/data/templates.xml
odoo/addons/foodcoopbcn/i18n/ca.po
odoo/addons/foodcoopbcn/listeners/__init__.py
odoo/addons/foodcoopbcn/listeners/product_product_listener.py
odoo/addons/foodcoopbcn/listeners/product_template_listener.py
odoo/addons/foodcoopbcn/models/__init__.py
odoo/addons/foodcoopbcn/models/product_category.py
odoo/addons/foodcoopbcn/models/product_product.py
odoo/addons/foodcoopbcn/models/product_template.py
odoo/addons/foodcoopbcn/models/purchase.py
odoo/addons/foodcoopbcn/models/stock_move.py
odoo/addons/foodcoopbcn/models/stock_move_line.py
odoo/addons/foodcoopbcn/models/stock_production_lot.py
odoo/addons/foodcoopbcn/models/subscription_request.py
odoo/addons/foodcoopbcn/report/layout.xml
odoo/addons/foodcoopbcn/report/product_label.xml
odoo/addons/foodcoopbcn/report/product_reports.xml
odoo/addons/foodcoopbcn/report/same_product_label.xml
odoo/addons/foodcoopbcn/static/src/fonts/AvenirNextCondensed-DemiBold.ttf
odoo/addons/foodcoopbcn/static/src/fonts/avenir-next-lt-pro-bold-condensed.otf
odoo/addons/foodcoopbcn/static/src/fonts/avenir-next-lt-pro-condensed-italic.otf
odoo/addons/foodcoopbcn/static/src/fonts/avenir-next-lt-pro-condensed.otf
odoo/addons/foodcoopbcn/static/src/xml/pos.xml
odoo/addons/foodcoopbcn/views/become_company_cooperator_view.xml
odoo/addons/foodcoopbcn/views/become_cooperator_view.xml
odoo/addons/foodcoopbcn/views/product_category_view.xml
odoo/addons/foodcoopbcn/views/stock_move_line_view.xml
odoo/addons/foodcoopbcn/views/subscription_request_view.xml
odoo12_addon_foodcoopbcn-12.0.0.0.18.dist-info/METADATA
odoo12_addon_foodcoopbcn-12.0.0.0.18.dist-info/WHEEL
odoo12_addon_foodcoopbcn-12.0.0.0.18.dist-info/top_level.txt
odoo12_addon_foodcoopbcn-12.0.0.0.18.dist-info/RECORD
